schema_mapper/__init__.py
schema_mapper/__version__.py
schema_mapper/canonical.py
schema_mapper/cli.py
schema_mapper/core.py
schema_mapper/ddl_mappings.py
schema_mapper/generators.py
schema_mapper/preprocessor.py
schema_mapper/profiler.py
schema_mapper/type_mappings.py
schema_mapper/utils.py
schema_mapper/validation_rules.py
schema_mapper/validators.py
schema_mapper/visualization.py
schema_mapper/yaml_schema.py
schema_mapper/connections/__init__.py
schema_mapper/connections/base.py
schema_mapper/connections/config.py
schema_mapper/connections/exceptions.py
schema_mapper/connections/factory.py
schema_mapper/connections/introspection.py
schema_mapper/connections/platform_connectors/__init__.py
schema_mapper/connections/platform_connectors/bigquery.py
schema_mapper/connections/platform_connectors/postgresql.py
schema_mapper/connections/platform_connectors/redshift.py
schema_mapper/connections/platform_connectors/snowflake.py
schema_mapper/connections/platform_connectors/sqlserver.py
schema_mapper/connections/utils/__init__.py
schema_mapper/connections/utils/pooling.py
schema_mapper/connections/utils/retry.py
schema_mapper/connections/utils/type_mapping.py
schema_mapper/connections/utils/validation.py
schema_mapper/incremental/__init__.py
schema_mapper/incremental/incremental_base.py
schema_mapper/incremental/key_detection.py
schema_mapper/incremental/patterns.py
schema_mapper/incremental/platform_generators/__init__.py
schema_mapper/incremental/platform_generators/bigquery.py
schema_mapper/incremental/platform_generators/postgresql.py
schema_mapper/incremental/platform_generators/redshift.py
schema_mapper/incremental/platform_generators/snowflake.py
schema_mapper/incremental/platform_generators/sqlserver.py
schema_mapper/renderers/__init__.py
schema_mapper/renderers/base.py
schema_mapper/renderers/bigquery.py
schema_mapper/renderers/factory.py
schema_mapper/renderers/postgresql.py
schema_mapper/renderers/redshift.py
schema_mapper/renderers/snowflake.py
schema_mapper-1.4.1.dist-info/licenses/LICENSE
schema_mapper-1.4.1.dist-info/METADATA
schema_mapper-1.4.1.dist-info/WHEEL
schema_mapper-1.4.1.dist-info/entry_points.txt
schema_mapper-1.4.1.dist-info/top_level.txt
schema_mapper-1.4.1.dist-info/RECORD
