Metadata-Version: 2.4
Name: schema-mapper
Version: 1.4.1
Summary: Production-grade ETL toolkit with ML feature engineering, intelligent data profiling, and unified database connections for BigQuery, Snowflake, Redshift, SQL Server, and PostgreSQL
Home-page: https://github.com/datateamsix/schema-mapper
Author: DataTeamSix
Author-email: DataTeamSix <research@dt6.io>
License: MIT
Project-URL: Homepage, https://github.com/datateamsix/schema-mapper
Project-URL: Documentation, https://github.com/datateamsix/schema-mapper#readme
Project-URL: Repository, https://github.com/datateamsix/schema-mapper
Project-URL: Bug Tracker, https://github.com/datateamsix/schema-mapper/issues
Keywords: database,schema,bigquery,snowflake,redshift,etl
Classifier: Development Status :: 5 - Production/Stable
Classifier: Intended Audience :: Developers
Classifier: License :: OSI Approved :: MIT License
Classifier: Programming Language :: Python :: 3
Classifier: Programming Language :: Python :: 3.8
Classifier: Programming Language :: Python :: 3.9
Classifier: Programming Language :: Python :: 3.10
Classifier: Programming Language :: Python :: 3.11
Classifier: Programming Language :: Python :: 3.12
Requires-Python: >=3.8
License-File: LICENSE
Requires-Dist: pandas>=2.0.0
Requires-Dist: numpy>=1.24.0
Requires-Dist: pyyaml>=6.0.0
Requires-Dist: python-dotenv>=1.0.0
Provides-Extra: dev
Requires-Dist: pytest>=7.0.0; extra == "dev"
Requires-Dist: pytest-cov>=4.0.0; extra == "dev"
Requires-Dist: black>=23.0.0; extra == "dev"
Requires-Dist: flake8>=6.0.0; extra == "dev"
Requires-Dist: mypy>=1.0.0; extra == "dev"
Provides-Extra: bigquery
Requires-Dist: google-cloud-bigquery>=3.0.0; extra == "bigquery"
Requires-Dist: pandas-gbq>=0.19.0; extra == "bigquery"
Provides-Extra: snowflake
Requires-Dist: snowflake-connector-python>=3.0.0; extra == "snowflake"
Provides-Extra: redshift
Requires-Dist: redshift-connector>=2.0.0; extra == "redshift"
Provides-Extra: sqlserver
Requires-Dist: pyodbc>=4.0.0; extra == "sqlserver"
Provides-Extra: postgresql
Requires-Dist: psycopg2-binary>=2.9.0; extra == "postgresql"
Provides-Extra: ml
Requires-Dist: tensorflow>=2.12.0; extra == "ml"
Requires-Dist: scikit-learn>=1.2.0; extra == "ml"
Provides-Extra: all
Requires-Dist: google-cloud-bigquery>=3.0.0; extra == "all"
Requires-Dist: pandas-gbq>=0.19.0; extra == "all"
Requires-Dist: snowflake-connector-python>=3.0.0; extra == "all"
Requires-Dist: redshift-connector>=2.0.0; extra == "all"
Requires-Dist: psycopg2-binary>=2.9.0; extra == "all"
Requires-Dist: pyodbc>=4.0.0; extra == "all"
Requires-Dist: tensorflow>=2.12.0; extra == "all"
Requires-Dist: scikit-learn>=1.2.0; extra == "all"
Dynamic: author
Dynamic: home-page
Dynamic: license-file
Dynamic: requires-python
